smartapi/__init__.py
smartapi/cli.py
smartapi/commands/__init__.py
smartapi/commands/app_run.py
smartapi/commands/db_migrate.py
smartapi/commands/db_rollback.py
smartapi/commands/init.py
smartapi/commands/make_controller.py
smartapi/commands/make_crud.py
smartapi/commands/make_job.py
smartapi/commands/make_migration.py
smartapi/commands/make_model.py
smartapi/commands/make_module.py
smartapi/commands/make_router.py
smartapi/commands/make_schema.py
smartapi/commands/make_service.py
smartapi/templates/controller/controller.py.tpl
smartapi/templates/crud/controller.base.py.tpl
smartapi/templates/crud/controller.methods.py.tpl
smartapi/templates/crud/model.py.tpl
smartapi/templates/crud/router.routes.py.tpl
smartapi/templates/crud/schema.py.tpl
smartapi/templates/crud/service.py.tpl
smartapi/templates/init/.env.example.tpl
smartapi/templates/init/.env.tpl
smartapi/templates/init/README.md.tpl
smartapi/templates/init/alembic.ini.tpl
smartapi/templates/init/api.Dockerfile.tpl
smartapi/templates/init/async_db.py.tpl
smartapi/templates/init/base.py.tpl
smartapi/templates/init/celery_app.py.tpl
smartapi/templates/init/config.py.tpl
smartapi/templates/init/controller.py.tpl
smartapi/templates/init/docker-compose.yml.tpl
smartapi/templates/init/gitignore.tpl
smartapi/templates/init/main.py.tpl
smartapi/templates/init/models.py.tpl
smartapi/templates/init/requirements.txt.tpl
smartapi/templates/init/security.py.tpl
smartapi/templates/init/sync_db.py.tpl
smartapi/templates/init/worker.py.tpl
smartapi/templates/jobs/job.py.tpl
smartapi/templates/model/model.py.tpl
smartapi/templates/module/controller.py.tpl
smartapi/templates/module/router.py.tpl
smartapi/templates/router/router.py.tpl
smartapi/templates/schema/schema.py.tpl
smartapi/templates/service/service.py.tpl
smartapi/utils/naming.py
smartapi/utils/project.py
smartapi/utils/templates.py
smartapi_cli-0.1.5.dist-info/licenses/LICENSE
smartapi_cli-0.1.5.dist-info/METADATA
smartapi_cli-0.1.5.dist-info/PKG-INFO 2
smartapi_cli-0.1.5.dist-info/SOURCES 2.txt
smartapi_cli-0.1.5.dist-info/WHEEL
smartapi_cli-0.1.5.dist-info/dependency_links 2.txt
smartapi_cli-0.1.5.dist-info/entry_points 2.txt
smartapi_cli-0.1.5.dist-info/entry_points.txt
smartapi_cli-0.1.5.dist-info/requires 2.txt
smartapi_cli-0.1.5.dist-info/top_level 2.txt
smartapi_cli-0.1.5.dist-info/top_level.txt
smartapi_cli-0.1.5.dist-info/RECORD
