Metadata-Version: 2.4
Name: smartapi-cli
Version: 0.1.5
Summary: Opinionated FastAPI CLI for scalable Python APIs
Author-email: Arthur Rezende <arezendealmeida@gmail.com>
License: MIT License
Requires-Python: >=3.10
License-File: LICENSE
Requires-Dist: typer
Dynamic: license-file
